find_stuff/__init__.py
find_stuff/__main__.py
find_stuff/__version__.py
find_stuff/cli.py
find_stuff/indexing.py
find_stuff/models.py
find_stuff/navigation.py
find_stuff-0.1.4.dist-info/licenses/LICENSE
tests/__init__.py
tests/conftest.py
tests/test_cli.py
tests/test_cli_browse_helpers.py
tests/test_indexing.py
tests/test_models.py
find_stuff-0.1.4.dist-info/METADATA
find_stuff-0.1.4.dist-info/WHEEL
find_stuff-0.1.4.dist-info/entry_points.txt
find_stuff-0.1.4.dist-info/top_level.txt
find_stuff-0.1.4.dist-info/RECORD
