Metadata-Version: 2.4
Name: find-stuff
Version: 0.1.4
Summary: Lightweight code search for your own projects.
Author-email: Nicu Tofan <nicu.tofan@gmail.com>
License: BSD 3-Clause License
Project-URL: Homepage, https://github.com/pyl1b/find-stuff
Project-URL: Repository, https://github.com/pyl1b/find-stuff
Project-URL: Changelog, https://github.com/pyl1b/find-stuff/blob/main/CHANGELOG.md
Project-URL: Issues, https://github.com/pyl1b/find-stuff/issues
Project-URL: Documentation, https://github.com/pyl1b/find-stuff/blob/main/README.md
Classifier: Operating System :: OS Independent
Classifier: Programming Language :: Python :: 3 :: Only
Classifier: Development Status :: 3 - Alpha
Classifier: License :: Other/Proprietary License
Classifier: Typing :: Typed
Requires-Python: >=3.11
License-File: LICENSE
Requires-Dist: click<9,>=8.1.8
Requires-Dist: dotenv>=0.9.9
Requires-Dist: sqlalchemy<3,>=2.0
Requires-Dist: requests<3,>=2.32.3
Requires-Dist: beautifulsoup4<5,>=4.12
Requires-Dist: attrs<26,>=23
Requires-Dist: pyyaml<7,>=6.0
Requires-Dist: openpyxl<4,>=3.1
Requires-Dist: InquirerPy<0.4,>=0.3.4
Requires-Dist: colorama<0.5,>=0.4.6
Provides-Extra: dev
Requires-Dist: ruff; extra == "dev"
Requires-Dist: build; extra == "dev"
Requires-Dist: mypy<2,>=1.8; extra == "dev"
Requires-Dist: pre-commit; extra == "dev"
Requires-Dist: pytest-cov; extra == "dev"
Requires-Dist: pytest-mock; extra == "dev"
Requires-Dist: pytest; extra == "dev"
Requires-Dist: twine; extra == "dev"
Requires-Dist: wheel; extra == "dev"
Requires-Dist: types-requests; extra == "dev"
Requires-Dist: types-PyYAML; extra == "dev"
Requires-Dist: types-openpyxl; extra == "dev"
Dynamic: license-file
